matchy/__init__.py
matchy/cli.py
matchy/helper_functions.py
matchy/matching_algorithms/__init__.py
matchy/matching_algorithms/base_matching_class.py
matchy/matching_algorithms/do_nothing.py
matchy/matching_algorithms/hill_climbing.py
matchy/matching_algorithms/random_hill.py
matchy/matching_algorithms/random_search.py
matchy/pretty_print.py
matchy-0.1.1.dist-info/entry_points.txt
matchy-0.1.1.dist-info/LICENSE
matchy-0.1.1.dist-info/WHEEL
matchy-0.1.1.dist-info/METADATA
matchy-0.1.1.dist-info/RECORD
