Metadata-Version: 2.1
Name: matchy
Version: 0.1.1
Summary: A tool for matching analog IC layout designs.
Home-page: https://github.com/ftorres16/matchy
License: MIT
Author: Fabian Torres
Requires-Python: >=3.8,<4.0
Classifier: License :: OSI Approved :: MIT License
Classifier: Programming Language :: Python :: 3
Classifier: Programming Language :: Python :: 3.10
Classifier: Programming Language :: Python :: 3.8
Classifier: Programming Language :: Python :: 3.9
Requires-Dist: click (>=8.1.3,<9.0.0)
Requires-Dist: numpy (>=1.23.2,<2.0.0)
Project-URL: Repository, https://github.com/ftorres16/matchy
